celparser/__init__.py
celparser/ast.py
celparser/errors.py
celparser/evaluator.py
celparser/lexer.py
celparser/parser.py
celparser-0.1.2.dist-info/licenses/LICENSE
tests/__init__.py
tests/test_evaluator.py
tests/test_lexer.py
tests/test_parser.py
celparser-0.1.2.dist-info/METADATA
celparser-0.1.2.dist-info/WHEEL
celparser-0.1.2.dist-info/top_level.txt
celparser-0.1.2.dist-info/RECORD
