Metadata-Version: 2.4
Name: celparser
Version: 0.1.2
Summary: Python parser and evaluator for Google Common Expression Language (CEL)
Home-page: https://github.com/mrb101/celparser
Author: Bassel J. Hamadeh
Author-email: "Bassel J. Hamadeh" <hamadeh.basel@gmail.com>
License: MIT
Project-URL: Homepage, https://github.com/mrb101/celparser
Project-URL: Repository, https://github.com/mrb101/celparser
Project-URL: Issues, https://github.com/mrb101/celparser/issues
Classifier: Development Status :: 3 - Alpha
Classifier: Intended Audience :: Developers
Classifier: License :: OSI Approved :: MIT License
Classifier: Programming Language :: Python :: 3
Classifier: Programming Language :: Python :: 3.8
Classifier: Programming Language :: Python :: 3.9
Classifier: Programming Language :: Python :: 3.10
Classifier: Topic :: Software Development :: Libraries :: Python Modules
Requires-Python: >=3.11
License-File: LICENSE
Requires-Dist: flask==3.1.0
Provides-Extra: dev
Requires-Dist: ruff>=0.11.3; extra == "dev"
Requires-Dist: pytest>=8.2.2; extra == "dev"
Requires-Dist: sphinx>=7.3.7; extra == "dev"
Dynamic: author
Dynamic: home-page
Dynamic: license-file
Dynamic: requires-python
